{"cameraMode":{"drawMode":0,"name":"Shaded","section":"Shading Mode"},"sceneLighting":false,"audioPlay":false,"sceneViewState":{"m_AlwaysRefresh":false,"showFog":true,"showSkybox":false,"showFlares":true,"showImageEffects":true,"showParticleSystems":true,"showVisualEffectGraphs":true,"m_FxEnabled":true},"in2DMode":false,"pivot":{"x":425.5,"y":239.39999389648438,"z":0.0},"rotation":{"x":-0.0019620077218860389,"y":0.9940750598907471,"z":-0.10718551278114319,"w":-0.018192166462540628},"size":488.22393798828127,"orthographic":false}